text2kgh_prompts/__init__.py
text2kgh_prompts/asserts.py
text2kgh_prompts/concat.py
text2kgh_prompts/concat_postprocess.py
text2kgh_prompts/core.py
text2kgh_prompts/postprocessors.py
text2kgh_prompts/utils.py
text2kgh_prompts-0.1.6.dist-info/METADATA
text2kgh_prompts-0.1.6.dist-info/WHEEL
text2kgh_prompts-0.1.6.dist-info/top_level.txt
text2kgh_prompts-0.1.6.dist-info/RECORD
