Metadata-Version: 2.4
Name: text2kgh-prompts
Version: 0.1.6
Summary: Add your description here
Requires-Python: >=3.10
Requires-Dist: llmada>=1.0.3
Requires-Dist: toml==0.10.2
